gpt_image/__init__.py
gpt_image/disk.py
gpt_image/entry.py
gpt_image/geometry.py
gpt_image/partition.py
gpt_image/table.py
tests/__init__.py
tests/test_disk.py
tests/test_entry.py
tests/test_geometry.py
tests/test_integration.py
tests/test_partition.py
tests/test_table.py
python_gpt_image-0.4.0.dist-info/LICENSE
python_gpt_image-0.4.0.dist-info/METADATA
python_gpt_image-0.4.0.dist-info/WHEEL
python_gpt_image-0.4.0.dist-info/top_level.txt
python_gpt_image-0.4.0.dist-info/RECORD
