Metadata-Version: 2.1
Name: python-gpt-image
Version: 0.4.0
Summary: Build GPT Disk Images on Local Drives
Home-page: https://github.com/swysocki/gpt-image
Author: Scott Wysocki
Author-email: swysocki@gmail.com
License: MIT
Platform: UNKNOWN
Requires-Python: >=3.6
License-File: LICENSE
